textlytics/__init__.py
textlytics-1.0.1.dist-info/LICENSE.txt
textlytics-1.0.1.dist-info/METADATA
textlytics-1.0.1.dist-info/WHEEL
textlytics-1.0.1.dist-info/top_level.txt
textlytics-1.0.1.dist-info/RECORD
