Metadata-Version: 2.1
Name: textlytics
Version: 1.0.1
Summary: TEXTLYTICS -- the Text Analytics Toolkit
Home-page: https://gitlab.com/jorgeluizfigueira/python-textlytics/
Author: Jorge Luiz Figueira
Author-email: jorgeluizfigueira@gmail.com
Maintainer: Jorge Luiz Figueira
Maintainer-email: jorgeluizfigueira@gmail.com
License: GPLV3+
Keywords: text complexity,text readability,natural language processing,computational linguistics,part of speech,linguistics,language,natural language,text analytics
Platform: UNKNOWN
Classifier: Development Status :: 3 - Alpha
Classifier: Intended Audience :: Science/Research
Classifier: Topic :: Scientific/Engineering :: Information Analysis
Classifier: License :: OSI Approved :: GNU General Public License v3 or later (GPLv3+)
Classifier: Programming Language :: Python :: 3
Requires-Python: >=3
Requires-Dist: pandas
Requires-Dist: Pyphen
Requires-Dist: syllables
Requires-Dist: nltk
Requires-Dist: nlpnet
